hive_vectorizer-1.0.0.dist-info/licenses/LICENSE
tests/__init__.py
tests/quick_test.py
tests/run_tests.py
tests/test_client_integration.py
tests/test_discovery.py
tests/test_exceptions.py
tests/test_file_operations.py
tests/test_http_client.py
tests/test_intelligent_search.py
tests/test_models.py
tests/test_sdk_comprehensive.py
tests/test_simple.py
tests/test_umicp.py
tests/test_validation.py
utils/__init__.py
utils/http_client.py
utils/transport.py
utils/umicp_client.py
utils/validation.py
hive_vectorizer-1.0.0.dist-info/METADATA
hive_vectorizer-1.0.0.dist-info/WHEEL
hive_vectorizer-1.0.0.dist-info/entry_points.txt
hive_vectorizer-1.0.0.dist-info/top_level.txt
hive_vectorizer-1.0.0.dist-info/RECORD
